modelgauge/aggregations.py
modelgauge/annotation.py
modelgauge/annotation_pipeline.py
modelgauge/annotator.py
modelgauge/annotator_registry.py
modelgauge/annotators/README.md
modelgauge/annotators/llama_guard_annotator.py
modelgauge/api_server.py
modelgauge/base_test.py
modelgauge/caching.py
modelgauge/command_line.py
modelgauge/concurrency.py
modelgauge/config.py
modelgauge/config_templates/secrets.toml
modelgauge/data_packing.py
modelgauge/dependency_helper.py
modelgauge/dependency_injection.py
modelgauge/external_data.py
modelgauge/general.py
modelgauge/instance_factory.py
modelgauge/load_plugins.py
modelgauge/main.py
modelgauge/multiple_choice_questions.py
modelgauge/not_implemented.py
modelgauge/pipeline.py
modelgauge/pipeline_runner.py
modelgauge/prompt.py
modelgauge/prompt_formatting.py
modelgauge/prompt_pipeline.py
modelgauge/record_init.py
modelgauge/records.py
modelgauge/runners/README.md
modelgauge/secret_values.py
modelgauge/simple_test_runner.py
modelgauge/single_turn_prompt_response.py
modelgauge/sut.py
modelgauge/sut_capabilities.py
modelgauge/sut_capabilities_verification.py
modelgauge/sut_decorator.py
modelgauge/sut_registry.py
modelgauge/suts/README.md
modelgauge/suts/together_cli.py
modelgauge/suts/together_client.py
modelgauge/test_decorator.py
modelgauge/test_registry.py
modelgauge/tests/README.md
modelgauge/tests/safe.py
modelgauge/tests/safe_v1.py
modelgauge/tests/specifications/README.md
modelgauge/tracked_object.py
modelgauge/typed_data.py
modelgauge-0.6.3.dist-info/LICENSE.md
modelgauge-0.6.3.dist-info/METADATA
modelgauge-0.6.3.dist-info/WHEEL
modelgauge-0.6.3.dist-info/entry_points.txt
modelgauge-0.6.3.dist-info/RECORD
