Metadata-Version: 2.1
Name: modelgauge
Version: 0.6.3
Summary: Automatically and uniformly measure the behavior of many AI Systems.
Home-page: https://github.com/mlcommons/modelgauge
License: Apache-2.0
Keywords: AI,GenAI,LLM,NLP,evaluate,measure,quality,testing,prompt,safety,compare,artificial,intelligence,Large,Language,Models
Author: MLCommons AI Safety
Author-email: ai-safety-engineering@mlcommons.org
Requires-Python: >=3.10,<4.0
Classifier: Development Status :: 4 - Beta
Classifier: Intended Audience :: Developers
Classifier: Intended Audience :: Information Technology
Classifier: Intended Audience :: Science/Research
Classifier: License :: OSI Approved :: Apache Software License
Classifier: Natural Language :: English
Classifier: Operating System :: OS Independent
Classifier: Programming Language :: Python :: 3
Classifier: Programming Language :: Python :: 3.10
Classifier: Programming Language :: Python :: 3.11
Classifier: Programming Language :: Python :: 3.12
Classifier: Topic :: Scientific/Engineering
Classifier: Topic :: Scientific/Engineering :: Artificial Intelligence
Classifier: Topic :: Software Development :: Libraries :: Python Modules
Classifier: Topic :: System :: Benchmark
Classifier: Typing :: Typed
Provides-Extra: all-plugins
Provides-Extra: demo
Provides-Extra: huggingface
Provides-Extra: openai
Provides-Extra: perspective-api
Provides-Extra: standard-tests
Requires-Dist: click (>=8.1.7,<9.0.0)
Requires-Dist: diskcache (>=5.6.3,<6.0.0)
Requires-Dist: fastapi (>=0.111.1,<0.112.0)
Requires-Dist: gdown (>=5.1.0)
Requires-Dist: jsonlines (>=4.0.0,<5.0.0)
Requires-Dist: modelgauge_demo_plugin ; extra == "demo" or extra == "all-plugins"
Requires-Dist: modelgauge_huggingface ; extra == "huggingface" or extra == "all-plugins"
Requires-Dist: modelgauge_openai ; extra == "openai" or extra == "all-plugins"
Requires-Dist: modelgauge_perspective_api ; extra == "perspective-api" or extra == "all-plugins"
Requires-Dist: modelgauge_standard_tests ; extra == "standard-tests" or extra == "all-plugins"
Requires-Dist: pydantic (>=2.6.0,<3.0.0)
Requires-Dist: sqlitedict (>=2.1.0,<3.0.0)
Requires-Dist: starlette (>=0.37.2,<0.38.0)
Requires-Dist: tenacity (>=8.3.0,<9.0.0)
Requires-Dist: together (>=1.2.3,<2.0.0)
Requires-Dist: tomli (>=2.0.1,<3.0.0)
Requires-Dist: tqdm (>=4.66.1)
Requires-Dist: types-tqdm (>=4.66.0.0,<5.0.0.0)
Requires-Dist: typing-extensions (>=4.10.0,<5.0.0)
Requires-Dist: zstandard (>=0.18.0,<0.19.0)
Project-URL: Repository, https://github.com/mlcommons/modelgauge
